agroecometrics/__init__.py
agroecometrics/data.py
agroecometrics/equations.py
agroecometrics/visualizations.py
agroecometrics-0.1.1.dist-info/METADATA
agroecometrics-0.1.1.dist-info/WHEEL
agroecometrics-0.1.1.dist-info/top_level.txt
agroecometrics-0.1.1.dist-info/RECORD
