Metadata-Version: 2.4
Name: agroecometrics
Version: 0.1.1
Summary: Agricultural ecology metrics and visualization tools.
Author-email: Scarlett Olson <Scarlett.W.Olson@gmail.com>
License-Expression: MIT
Project-URL: Homepage, https://github.com/wiscbicklab/agro-eco-metrics
Project-URL: Bug Tracker, https://github.com/wiscbicklab/agro-eco-metrics/issues
Project-URL: Documentation, https://wiscbicklab.github.io/AgroEcoMetrics
Requires-Python: >=3.7
Requires-Dist: matplotlib
Requires-Dist: pandas
Requires-Dist: numpy
Requires-Dist: bokeh
Requires-Dist: scikit-learn
